CHANGELOG.txt
LICENCE.txt
MANIFEST.in
README.txt
__init__.py
setup.py
TOPSIS_Ayush_101803401/topsis.py
TOPSIS_Ayush_101803401.egg-info/PKG-INFO
TOPSIS_Ayush_101803401.egg-info/SOURCES.txt
TOPSIS_Ayush_101803401.egg-info/dependency_links.txt
TOPSIS_Ayush_101803401.egg-info/top_level.txt