Metadata-Version: 1.1
Name: TOPSIS-Ayush-101803401
Version: 0.0.1
Summary: A very basic file of topsis
Home-page: UNKNOWN
Author: AYUSH
Author-email: ayush15goel@gmail.com
License: MIT
Keywords: topsis
Platform: UNKNOWN
Classifier: Development Status :: 5 - Production/Stable
Classifier: Intended Audience :: Education
Classifier: Operating System :: Microsoft :: Windows :: Windows 10
Classifier: License :: OSI Approved :: MIT License
Classifier: Programming Language :: Python :: 3
